{"trial_id": "144ca9e89fca81a676548e1e214dc666", "hyperparameters": {"space": [{"class_name": "Boolean", "config": {"name": "structured_data_block_1/normalize", "default": false, "conditions": []}}, {"class_name": "Choice", "config": {"name": "structured_data_block_1/dense_block_1/num_layers", "default": 2, "conditions": [], "values": [1, 2, 3], "ordered": true}}, {"class_name": "Boolean", "config": {"name": "structured_data_block_1/dense_block_1/use_batchnorm", "default": false, "conditions": []}}, {"class_name": "Choice", "config": {"name": "structured_data_block_1/dense_block_1/dropout", "default": 0, "conditions": [], "values": [0.0, 0.25, 0.5], "ordered": true}}, {"class_name": "Choice", "config": {"name": "structured_data_block_1/dense_block_1/units_0", "default": 32, "conditions": [], "values": [16, 32, 64, 128, 256, 512, 1024], "ordered": true}}, {"class_name": "Choice", "config": {"name": "structured_data_block_1/dense_block_1/units_1", "default": 32, "conditions": [], "values": [16, 32, 64, 128, 256, 512, 1024], "ordered": true}}, {"class_name": "Choice", "config": {"name": "classification_head_1/dropout", "default": 0, "conditions": [], "values": [0.0, 0.25, 0.5], "ordered": true}}, {"class_name": "Choice", "config": {"name": "optimizer", "default": "adam", "conditions": [], "values": ["adam", "sgd", "adam_weight_decay"], "ordered": false}}, {"class_name": "Choice", "config": {"name": "learning_rate", "default": 0.001, "conditions": [], "values": [0.1, 0.01, 0.001, 0.0001, 2e-05, 1e-05], "ordered": true}}, {"class_name": "Choice", "config": {"name": "structured_data_block_1/dense_block_1/units_2", "default": 32, "conditions": [], "values": [16, 32, 64, 128, 256, 512, 1024], "ordered": true}}], "values": {"structured_data_block_1/normalize": true, "structured_data_block_1/dense_block_1/num_layers": 2, "structured_data_block_1/dense_block_1/use_batchnorm": false, "structured_data_block_1/dense_block_1/dropout": 0, "structured_data_block_1/dense_block_1/units_0": 32, "structured_data_block_1/dense_block_1/units_1": 32, "classification_head_1/dropout": 0.5, "optimizer": "adam_weight_decay", "learning_rate": 0.001, "structured_data_block_1/dense_block_1/units_2": 16}}, "metrics": {"metrics": {"loss": {"direction": "min", "observations": [{"value": [0.7529387474060059], "step": 0}, {"value": [0.7351923584938049], "step": 1}, {"value": [0.7453784942626953], "step": 2}, {"value": [0.7305449843406677], "step": 3}, {"value": [0.7456821799278259], "step": 4}, {"value": [0.7380290031433105], "step": 5}, {"value": [0.7383386492729187], "step": 6}, {"value": [0.7452204823493958], "step": 7}, {"value": [0.73713219165802], "step": 8}, {"value": [0.738883912563324], "step": 9}, {"value": [0.7422688007354736], "step": 10}]}, "accuracy": {"direction": "max", "observations": [{"value": [0.443359375], "step": 0}, {"value": [0.443359375], "step": 1}, {"value": [0.453125], "step": 2}, {"value": [0.494140625], "step": 3}, {"value": [0.458984375], "step": 4}, {"value": [0.462890625], "step": 5}, {"value": [0.458984375], "step": 6}, {"value": [0.466796875], "step": 7}, {"value": [0.4609375], "step": 8}, {"value": [0.4375], "step": 9}, {"value": [0.451171875], "step": 10}]}, "val_loss": {"direction": "min", "observations": [{"value": [0.7254839539527893], "step": 0}, {"value": [0.7254839539527893], "step": 1}, {"value": [0.7254839539527893], "step": 2}, {"value": [0.7254839539527893], "step": 3}, {"value": [0.7254839539527893], "step": 4}, {"value": [0.7254839539527893], "step": 5}, {"value": [0.7254839539527893], "step": 6}, {"value": [0.7254839539527893], "step": 7}, {"value": [0.7254839539527893], "step": 8}, {"value": [0.7254839539527893], "step": 9}, {"value": [0.7254839539527893], "step": 10}]}, "val_accuracy": {"direction": "max", "observations": [{"value": [0.4166666567325592], "step": 0}, {"value": [0.4166666567325592], "step": 1}, {"value": [0.4166666567325592], "step": 2}, {"value": [0.4166666567325592], "step": 3}, {"value": [0.4166666567325592], "step": 4}, {"value": [0.4166666567325592], "step": 5}, {"value": [0.4166666567325592], "step": 6}, {"value": [0.4166666567325592], "step": 7}, {"value": [0.4166666567325592], "step": 8}, {"value": [0.4166666567325592], "step": 9}, {"value": [0.4166666567325592], "step": 10}]}}}, "score": 0.4166666567325592, "best_step": 0, "status": "COMPLETED"}