{"trial_id": "5da044eddc5356f9fecf373f9a303e86", "hyperparameters": {"space": [{"class_name": "Boolean", "config": {"name": "structured_data_block_1/normalize", "default": false, "conditions": []}}, {"class_name": "Choice", "config": {"name": "structured_data_block_1/dense_block_1/num_layers", "default": 2, "conditions": [], "values": [1, 2, 3], "ordered": true}}, {"class_name": "Boolean", "config": {"name": "structured_data_block_1/dense_block_1/use_batchnorm", "default": false, "conditions": []}}, {"class_name": "Choice", "config": {"name": "structured_data_block_1/dense_block_1/dropout", "default": 0, "conditions": [], "values": [0.0, 0.25, 0.5], "ordered": true}}, {"class_name": "Choice", "config": {"name": "structured_data_block_1/dense_block_1/units_0", "default": 32, "conditions": [], "values": [16, 32, 64, 128, 256, 512, 1024], "ordered": true}}, {"class_name": "Choice", "config": {"name": "structured_data_block_1/dense_block_1/units_1", "default": 32, "conditions": [], "values": [16, 32, 64, 128, 256, 512, 1024], "ordered": true}}, {"class_name": "Choice", "config": {"name": "classification_head_1/dropout", "default": 0, "conditions": [], "values": [0.0, 0.25, 0.5], "ordered": true}}, {"class_name": "Choice", "config": {"name": "optimizer", "default": "adam", "conditions": [], "values": ["adam", "sgd", "adam_weight_decay"], "ordered": false}}, {"class_name": "Choice", "config": {"name": "learning_rate", "default": 0.001, "conditions": [], "values": [0.1, 0.01, 0.001, 0.0001, 2e-05, 1e-05], "ordered": true}}, {"class_name": "Choice", "config": {"name": "structured_data_block_1/dense_block_1/units_2", "default": 32, "conditions": [], "values": [16, 32, 64, 128, 256, 512, 1024], "ordered": true}}], "values": {"structured_data_block_1/normalize": true, "structured_data_block_1/dense_block_1/num_layers": 2, "structured_data_block_1/dense_block_1/use_batchnorm": true, "structured_data_block_1/dense_block_1/dropout": 0, "structured_data_block_1/dense_block_1/units_0": 32, "structured_data_block_1/dense_block_1/units_1": 32, "classification_head_1/dropout": 0.5, "optimizer": "adam", "learning_rate": 0.001, "structured_data_block_1/dense_block_1/units_2": 1024}}, "metrics": {"metrics": {"loss": {"direction": "min", "observations": [{"value": [0.7914636731147766], "step": 0}, {"value": [0.7181448340415955], "step": 1}, {"value": [0.5843716263771057], "step": 2}, {"value": [0.5591873526573181], "step": 3}, {"value": [0.5541873574256897], "step": 4}, {"value": [0.4811731278896332], "step": 5}, {"value": [0.48571765422821045], "step": 6}, {"value": [0.4564902186393738], "step": 7}, {"value": [0.4809104800224304], "step": 8}, {"value": [0.43408316373825073], "step": 9}, {"value": [0.4377366900444031], "step": 10}, {"value": [0.4359263777732849], "step": 11}, {"value": [0.43398869037628174], "step": 12}, {"value": [0.4127815067768097], "step": 13}, {"value": [0.41160106658935547], "step": 14}, {"value": [0.39867785573005676], "step": 15}, {"value": [0.3892301917076111], "step": 16}, {"value": [0.3874167203903198], "step": 17}, {"value": [0.39267680048942566], "step": 18}, {"value": [0.3874734044075012], "step": 19}, {"value": [0.3912654221057892], "step": 20}, {"value": [0.3861468732357025], "step": 21}, {"value": [0.3892517387866974], "step": 22}, {"value": [0.37911880016326904], "step": 23}]}, "accuracy": {"direction": "max", "observations": [{"value": [0.5234375], "step": 0}, {"value": [0.611328125], "step": 1}, {"value": [0.705078125], "step": 2}, {"value": [0.751953125], "step": 3}, {"value": [0.759765625], "step": 4}, {"value": [0.7890625], "step": 5}, {"value": [0.78125], "step": 6}, {"value": [0.796875], "step": 7}, {"value": [0.810546875], "step": 8}, {"value": [0.833984375], "step": 9}, {"value": [0.818359375], "step": 10}, {"value": [0.828125], "step": 11}, {"value": [0.830078125], "step": 12}, {"value": [0.828125], "step": 13}, {"value": [0.826171875], "step": 14}, {"value": [0.8359375], "step": 15}, {"value": [0.84375], "step": 16}, {"value": [0.84375], "step": 17}, {"value": [0.845703125], "step": 18}, {"value": [0.84765625], "step": 19}, {"value": [0.837890625], "step": 20}, {"value": [0.837890625], "step": 21}, {"value": [0.845703125], "step": 22}, {"value": [0.8515625], "step": 23}]}, "val_loss": {"direction": "min", "observations": [{"value": [0.6669145226478577], "step": 0}, {"value": [0.6274120807647705], "step": 1}, {"value": [0.5950125455856323], "step": 2}, {"value": [0.5662899017333984], "step": 3}, {"value": [0.5426537394523621], "step": 4}, {"value": [0.520763099193573], "step": 5}, {"value": [0.5036737322807312], "step": 6}, {"value": [0.4916928708553314], "step": 7}, {"value": [0.48369336128234863], "step": 8}, {"value": [0.47709333896636963], "step": 9}, {"value": [0.471169114112854], "step": 10}, {"value": [0.468790739774704], "step": 11}, {"value": [0.46742457151412964], "step": 12}, {"value": [0.46673494577407837], "step": 13}, {"value": [0.46783366799354553], "step": 14}, {"value": [0.4702945053577423], "step": 15}, {"value": [0.47187718749046326], "step": 16}, {"value": [0.47497713565826416], "step": 17}, {"value": [0.48216670751571655], "step": 18}, {"value": [0.48696768283843994], "step": 19}, {"value": [0.4919528365135193], "step": 20}, {"value": [0.4946209490299225], "step": 21}, {"value": [0.49749064445495605], "step": 22}, {"value": [0.49610814452171326], "step": 23}]}, "val_accuracy": {"direction": "max", "observations": [{"value": [0.5952380895614624], "step": 0}, {"value": [0.761904776096344], "step": 1}, {"value": [0.8095238208770752], "step": 2}, {"value": [0.8214285969734192], "step": 3}, {"value": [0.8095238208770752], "step": 4}, {"value": [0.8214285969734192], "step": 5}, {"value": [0.8214285969734192], "step": 6}, {"value": [0.8214285969734192], "step": 7}, {"value": [0.8214285969734192], "step": 8}, {"value": [0.8214285969734192], "step": 9}, {"value": [0.8214285969734192], "step": 10}, {"value": [0.8214285969734192], "step": 11}, {"value": [0.8214285969734192], "step": 12}, {"value": [0.8214285969734192], "step": 13}, {"value": [0.8214285969734192], "step": 14}, {"value": [0.8333333134651184], "step": 15}, {"value": [0.8333333134651184], "step": 16}, {"value": [0.8333333134651184], "step": 17}, {"value": [0.8333333134651184], "step": 18}, {"value": [0.8333333134651184], "step": 19}, {"value": [0.8333333134651184], "step": 20}, {"value": [0.8333333134651184], "step": 21}, {"value": [0.8452380895614624], "step": 22}, {"value": [0.8333333134651184], "step": 23}]}}}, "score": 0.8452380895614624, "best_step": 22, "status": "COMPLETED"}